LICENSE
MANIFEST.in
README.rst
park.py
setup.py
test_park.py
park.egg-info/PKG-INFO
park.egg-info/SOURCES.txt
park.egg-info/dependency_links.txt
park.egg-info/top_level.txt