Metadata-Version: 1.0
Name: park
Version: 0.9.1
Summary: A key-value store with ordered traversal of keys
Home-page: https://github.com/litl/park
Author: Peter Teichman
Author-email: pteichman@litl.com
License: MIT
Platform: UNKNOWN
Classifier: Development Status :: 5 - Production/Stable
Classifier: Intended Audience :: Developers
Classifier: License :: OSI Approved :: MIT License
Classifier: Operating System :: OS Independent
Classifier: Programming Language :: Python
